xlnet/__init__.py
xlnet/classifier_utils.py
xlnet/data_utils.py
xlnet/function_builder.py
xlnet/gpu_utils.py
xlnet/model_utils.py
xlnet/modeling.py
xlnet/prepro_utils.py
xlnet/run_classifier.py
xlnet/run_race.py
xlnet/run_squad.py
xlnet/squad_utils.py
xlnet/tpu_estimator.py
xlnet/train.py
xlnet/train_gpu.py
xlnet/xlnet.py
xlnet_tensorflow-1.1.2.dist-info/LICENSE
xlnet_tensorflow-1.1.2.dist-info/METADATA
xlnet_tensorflow-1.1.2.dist-info/WHEEL
xlnet_tensorflow-1.1.2.dist-info/top_level.txt
xlnet_tensorflow-1.1.2.dist-info/RECORD
