Metadata-Version: 2.1
Name: xlnet-tensorflow
Version: 1.1.2
Summary: XLNet fork of https://github.com/zihangdai/xlnet with package configuration
Home-page: https://github.com/zihangdai/xlnet
Author: sebisebi
Author-email: gpirtoaca@gmail.com
License: Apache 2.0
Platform: UNKNOWN
Classifier: Programming Language :: Python :: 3
Classifier: Programming Language :: Python :: 2
Classifier: License :: OSI Approved :: Apache Software License
Classifier: Operating System :: OS Independent
Classifier: Topic :: Scientific/Engineering
Classifier: Topic :: Scientific/Engineering :: Artificial Intelligence
Classifier: Topic :: Software Development :: Libraries :: Python Modules
Classifier: Development Status :: 5 - Production/Stable
Requires-Dist: six
Provides-Extra: absl-py
Requires-Dist: absl-py (>=0.7.0) ; extra == 'absl-py'
Provides-Extra: numpy
Requires-Dist: numpy (>=1.15.0) ; extra == 'numpy'
Provides-Extra: sentencepiece
Requires-Dist: sentencepiece (>=0.1.83) ; extra == 'sentencepiece'
Provides-Extra: tensorflow
Requires-Dist: tensorflow (>=1.13.1) ; extra == 'tensorflow'
